smartio/__init__.py
smartio/smartio.py
smartio-0.1.0.dist-info/METADATA
smartio-0.1.0.dist-info/WHEEL
smartio-0.1.0.dist-info/top_level.txt
smartio-0.1.0.dist-info/RECORD
